{
  "id": 9051503788283,
  "title": "Coilover for Volkswagen Jetta MK5 MK6 FWD 2006-2017 PS004110",
  "handle": "ps004110-ps-coilover-for-volkswagen-jetta-mk5-mk6-fwd-2006-2017",
  "description": "<h4>Application:</h4>\n<ul>\n<li>Volkswagen Jetta 5th Gen MK5/A5 2005-2011</li>\n<li>Volkswagen Jetta 6th Gen MK6/A6 2011-2019</li>\n<li>Volkswagen Golf 5th Gen (GTI, DTI) MK5/A5 2003-2009</li>\n<li>Volkswagen Golf 6th Gen <span style=\"text-decoration: underline;\"><strong>MK6/A6</strong></span> 2009-2012</li>\n</ul>\n<p data-path-to-node=\"2\"><span style=\"color: rgb(255, 42, 0);\"><b data-path-to-node=\"2\" data-index-in-node=\"0\">Product Fitment Notice:</b></span></p>\n<p data-path-to-node=\"3\">Please be advised that the <strong>PS004110</strong> products feature a <b data-path-to-node=\"3\" data-index-in-node=\"74\">55mm lower strut diameter</b> and are designed specifically for models requiring this size. If your vehicle requires a <b data-path-to-node=\"3\" data-index-in-node=\"189\">50mm lower strut</b>, this version will not be compatible. Please verify your vehicle's strut diameter before purchasing to ensure correct fitment.</p>\n<p> </p>\n<h4>Package Includes:</h4>\n<ul>\n<li>Front coilovers × 2 pcs</li>\n<li>Rear coilovers × 2 pcs</li>\n<li>wrench × 2 pcs</li>\n</ul>\n<h4>Features:</h4>\n<ul>\n<li>Mono-tube shock design, provide larger capacity of oil and gas</li>\n<li>Adjustable ride height</li>\n<li>Adjustable pre-load spring tension</li>\n<li>Hi Tensile performance spring - Under 600,000 times continuously test, the spring distortion is less than 0.04%. Plus, the special surface treatment is to improve the durability and performance.</li>\n<li>All inserts come with fitted rubber boots to protect the damper and keep clean.</li>\n<li>Improve your handling performance without sacrifice comfortable ride.</li>\n<li>A fast and affordable way to easily upgrade your car's appearance.</li>\n<li>Easy installation with right tools.</li>\n<li>Ideal for any track, drift and fast road and can also be used for daily driving.</li>\n<li>The accessories in the photos are included</li>\n<li>Default 1-year warranty for any manufacturing defect, upgrade to 2 years with our Extended Warranty Program</li>\n</ul>\n<h4>Technical Specifications:</h4>\n<ul>\n<li>Spring rate Front: 6 kg/mm</li>\n<li>Spring rate Rear: 6 kg/mm</li>\n<li>Adjustable height: Yes</li>\n<li>Adjustable camber plate: Only front coilovers</li>\n<li>Adjustable damper: Non Adjustable Damper Force</li>\n</ul>\n<h4>Warranty</h4>\n<p>All the items carry standard 1 year warranty from the date of purchase. Proof of purchases is required and it's better to send us your order number. Besides, in order to speed up warranty claim, please show us images and document as much as details. Pictures and videos are good enough at most time and we don't need the defected items back. Sometimes we may ask for more data to confirm what's the problem and it can help us to fix it better.</p>",
  "published_at": "2025-07-02T13:50:14+08:00",
  "created_at": "2025-07-02T13:50:20+08:00",
  "vendor": "FAPO",
  "type": "PS/PS+ Coilover",
  "tags": [],
  "price": 27900,
  "price_min": 27900,
  "price_max": 27900,
  "available": true,
  "price_varies": false,
  "compare_at_price": 31900,
  "compare_at_price_min": 31900,
  "compare_at_price_max": 31900,
  "compare_at_price_varies": false,
  "variants": [
    {
      "id": 47303623147771,
      "title": "Default Title",
      "option1": "Default Title",
      "option2": null,
      "option3": null,
      "sku": "PS004110",
      "requires_shipping": true,
      "taxable": false,
      "featured_image": null,
      "available": true,
      "name": "Coilover for Volkswagen Jetta MK5 MK6 FWD 2006-2017 PS004110",
      "public_title": null,
      "options": [
        "Default Title"
      ],
      "price": 27900,
      "weight": 21000,
      "compare_at_price": 31900,
      "inventory_management": "shopify",
      "barcode": null,
      "quantity_rule": {
        "min": 1,
        "max": null,
        "increment": 1
      },
      "quantity_price_breaks": [],
      "requires_selling_plan": false,
      "selling_plan_allocations": []
    }
  ],
  "images": [
    "//cdn.shopify.com/s/files/1/0764/7258/2395/files/30793f0ed847d7c9.jpg?v=1756719638",
    "//cdn.shopify.com/s/files/1/0764/7258/2395/files/2_c229703e-40ad-4f0e-a326-4f7c77ac2a15.jpg?v=1774859084",
    "//cdn.shopify.com/s/files/1/0764/7258/2395/files/e31a2bca665297dd_67d9461d-7f6b-4cf8-a744-c284260b4168.jpg?v=1774856126",
    "//cdn.shopify.com/s/files/1/0764/7258/2395/files/PS011310_7.jpg?v=1774856126",
    "//cdn.shopify.com/s/files/1/0764/7258/2395/files/PS011310_1.jpg?v=1774856126",
    "//cdn.shopify.com/s/files/1/0764/7258/2395/files/PS011310_2.jpg?v=1774856126",
    "//cdn.shopify.com/s/files/1/0764/7258/2395/files/cebd6d1b2d630eaa.jpg?v=1774856126",
    "//cdn.shopify.com/s/files/1/0764/7258/2395/files/fd2d3007234225bd.jpg?v=1774856126",
    "//cdn.shopify.com/s/files/1/0764/7258/2395/files/0da6ea785b474380.jpg?v=1774856126"
  ],
  "featured_image": "//cdn.shopify.com/s/files/1/0764/7258/2395/files/30793f0ed847d7c9.jpg?v=1756719638",
  "options": [
    {
      "name": "Title",
      "position": 1,
      "values": [
        "Default Title"
      ]
    }
  ],
  "url": "/products/ps004110-ps-coilover-for-volkswagen-jetta-mk5-mk6-fwd-2006-2017",
  "media": [
    {
      "alt": "PS004110 PS Coilover for Volkswagen Jetta MK5 MK6 FWD 2006-2017",
      "id": 39213562429691,
      "position": 1,
      "preview_image": {
        "aspect_ratio": 1.0,
        "height": 1500,
        "width": 1500,
        "src": "https://cdn.shopify.com/s/files/1/0764/7258/2395/files/30793f0ed847d7c9.jpg?v=1756719638"
      },
      "aspect_ratio": 1.0,
      "height": 1500,
      "media_type": "image",
      "src": "https://cdn.shopify.com/s/files/1/0764/7258/2395/files/30793f0ed847d7c9.jpg?v=1756719638",
      "width": 1500
    },
    {
      "alt": null,
      "id": 40905468248315,
      "position": 2,
      "preview_image": {
        "aspect_ratio": 1.0,
        "height": 1500,
        "width": 1500,
        "src": "https://cdn.shopify.com/s/files/1/0764/7258/2395/files/2_c229703e-40ad-4f0e-a326-4f7c77ac2a15.jpg?v=1774859084"
      },
      "aspect_ratio": 1.0,
      "height": 1500,
      "media_type": "image",
      "src": "https://cdn.shopify.com/s/files/1/0764/7258/2395/files/2_c229703e-40ad-4f0e-a326-4f7c77ac2a15.jpg?v=1774859084",
      "width": 1500
    },
    {
      "alt": null,
      "id": 39213562527995,
      "position": 3,
      "preview_image": {
        "aspect_ratio": 1.0,
        "height": 1500,
        "width": 1500,
        "src": "https://cdn.shopify.com/s/files/1/0764/7258/2395/files/e31a2bca665297dd_67d9461d-7f6b-4cf8-a744-c284260b4168.jpg?v=1774856126"
      },
      "aspect_ratio": 1.0,
      "height": 1500,
      "media_type": "image",
      "src": "https://cdn.shopify.com/s/files/1/0764/7258/2395/files/e31a2bca665297dd_67d9461d-7f6b-4cf8-a744-c284260b4168.jpg?v=1774856126",
      "width": 1500
    },
    {
      "alt": null,
      "id": 39712590627067,
      "position": 4,
      "preview_image": {
        "aspect_ratio": 1.0,
        "height": 1500,
        "width": 1500,
        "src": "https://cdn.shopify.com/s/files/1/0764/7258/2395/files/PS011310_7.jpg?v=1774856126"
      },
      "aspect_ratio": 1.0,
      "height": 1500,
      "media_type": "image",
      "src": "https://cdn.shopify.com/s/files/1/0764/7258/2395/files/PS011310_7.jpg?v=1774856126",
      "width": 1500
    },
    {
      "alt": null,
      "id": 39712590758139,
      "position": 5,
      "preview_image": {
        "aspect_ratio": 1.0,
        "height": 1500,
        "width": 1500,
        "src": "https://cdn.shopify.com/s/files/1/0764/7258/2395/files/PS011310_1.jpg?v=1774856126"
      },
      "aspect_ratio": 1.0,
      "height": 1500,
      "media_type": "image",
      "src": "https://cdn.shopify.com/s/files/1/0764/7258/2395/files/PS011310_1.jpg?v=1774856126",
      "width": 1500
    },
    {
      "alt": null,
      "id": 39712590692603,
      "position": 6,
      "preview_image": {
        "aspect_ratio": 1.0,
        "height": 1500,
        "width": 1500,
        "src": "https://cdn.shopify.com/s/files/1/0764/7258/2395/files/PS011310_2.jpg?v=1774856126"
      },
      "aspect_ratio": 1.0,
      "height": 1500,
      "media_type": "image",
      "src": "https://cdn.shopify.com/s/files/1/0764/7258/2395/files/PS011310_2.jpg?v=1774856126",
      "width": 1500
    },
    {
      "alt": null,
      "id": 39213562495227,
      "position": 7,
      "preview_image": {
        "aspect_ratio": 1.0,
        "height": 1500,
        "width": 1500,
        "src": "https://cdn.shopify.com/s/files/1/0764/7258/2395/files/cebd6d1b2d630eaa.jpg?v=1774856126"
      },
      "aspect_ratio": 1.0,
      "height": 1500,
      "media_type": "image",
      "src": "https://cdn.shopify.com/s/files/1/0764/7258/2395/files/cebd6d1b2d630eaa.jpg?v=1774856126",
      "width": 1500
    },
    {
      "alt": null,
      "id": 39213562560763,
      "position": 8,
      "preview_image": {
        "aspect_ratio": 1.0,
        "height": 1500,
        "width": 1500,
        "src": "https://cdn.shopify.com/s/files/1/0764/7258/2395/files/fd2d3007234225bd.jpg?v=1774856126"
      },
      "aspect_ratio": 1.0,
      "height": 1500,
      "media_type": "image",
      "src": "https://cdn.shopify.com/s/files/1/0764/7258/2395/files/fd2d3007234225bd.jpg?v=1774856126",
      "width": 1500
    },
    {
      "alt": null,
      "id": 39213562593531,
      "position": 9,
      "preview_image": {
        "aspect_ratio": 1.0,
        "height": 1500,
        "width": 1500,
        "src": "https://cdn.shopify.com/s/files/1/0764/7258/2395/files/0da6ea785b474380.jpg?v=1774856126"
      },
      "aspect_ratio": 1.0,
      "height": 1500,
      "media_type": "image",
      "src": "https://cdn.shopify.com/s/files/1/0764/7258/2395/files/0da6ea785b474380.jpg?v=1774856126",
      "width": 1500
    }
  ],
  "requires_selling_plan": false,
  "selling_plan_groups": []
}